Camper/ExceptionCatcher.py
Camper/Log.py
Camper/Static.py
Camper/__init__.py
Camper_Logger_Exception-0.2.0.dist-info/LICENSE
Camper_Logger_Exception-0.2.0.dist-info/METADATA
Camper_Logger_Exception-0.2.0.dist-info/WHEEL
Camper_Logger_Exception-0.2.0.dist-info/top_level.txt
Camper_Logger_Exception-0.2.0.dist-info/RECORD
