Metadata-Version: 2.1
Name: Camper-Logger-Exception
Version: 0.2.0
Summary: Python logging and exception catcher library for lazy peoples
Home-page: https://github.com/abdullahkulcu/Camper-Logger-Exception
Author: Abdullah KULCU
Author-email: abdullahkulcu@outlook.com
License: UNKNOWN
Platform: UNKNOWN
Classifier: Programming Language :: Python :: 3.6
Classifier: License :: OSI Approved :: MIT License
Classifier: Operating System :: OS Independent
Requires-Dist: colorlog
Requires-Dist: requests
Requires-Dist: raven
